pttydev/__init__.py
pttydev/dev_serial.py
pttydev/dev_ws.py
pttydev/dev_wsapp.py
pttydev/pttydev.py
pttydev/sample.py
pttydev-0.0.6.dist-info/LICENSE
pttydev-0.0.6.dist-info/METADATA
pttydev-0.0.6.dist-info/WHEEL
pttydev-0.0.6.dist-info/top_level.txt
pttydev-0.0.6.dist-info/RECORD
