Metadata-Version: 2.1
Name: pttydev
Version: 0.0.6
Summary: TTYDev - Pseudo TTY Device
Home-page: https://github.com/kr-g/pttydev
Author: k.r. goger
Author-email: k.r.goger+{projectname}@gmail.com
License: MIT
Keywords: python threading pyserial websocket websocket-client micropython webrepl esp8266 esp32
Platform: UNKNOWN
Classifier: Development Status :: 3 - Alpha
Classifier: Operating System :: POSIX :: Linux
Classifier: Intended Audience :: Developers
Classifier: Programming Language :: Python :: 3
Classifier: License :: OSI Approved :: MIT License
Requires-Python: >=3.8
License-File: LICENSE
Requires-Dist: pyatomic (==0.0.2)
Requires-Dist: pyserial
Requires-Dist: websocket-client
